gpas/__init__.py
gpas/cli.py
gpas/constants.py
gpas/errors.py
gpas/http_helpers.py
gpas/log_utils.py
gpas/models.py
gpas/types.py
gpas/util.py
gpas/client/env.py
gpas/client/upload_client.py
gpas/tasks/__init__.py
gpas/tasks/authentication.py
gpas/tasks/download.py
gpas/tasks/prep_samples.py
gpas/tasks/query.py
gpas/tasks/upload.py
gpas/tasks/validate.py
gpas-3.0.1.dist-info/entry_points.txt
gpas-3.0.1.dist-info/licenses/LICENSE
gpas-3.0.1.dist-info/WHEEL
gpas-3.0.1.dist-info/METADATA
gpas-3.0.1.dist-info/RECORD
