Metadata-Version: 2.4
Name: gpas
Version: 3.0.1
Summary: The command line and Python client for GPAS.
Keywords: gpas,global pathogen analysis service,pathogen,pathogena,eit
Author-email: GPAS Devs <gpas.support@eit.org>
Maintainer-email: GPAS Devs <gpas.support@eit.org>
Requires-Python: >=3.10
License-File: LICENSE
Requires-Dist: httpx>=0.27.0
Requires-Dist: packaging>=23.2
Requires-Dist: platformdirs>=3.9.1,<=4.2.0
Requires-Dist: tqdm==4.66.3
Requires-Dist: pydantic>=2.6.2,<3
Requires-Dist: tenacity==8.2.3
Requires-Dist: python-dotenv>=1.0
Requires-Dist: pytest-mock>=3.14.0
Requires-Dist: rich-click>=1.8.9
Requires-Dist: auth0-python>=4.10.0
Requires-Dist: flit>=3.9.0 ; extra == "dev"
Requires-Dist: mypy>=1.18.2 ; extra == "dev"
Requires-Dist: pre-commit>=4.0.1 ; extra == "dev"
Requires-Dist: pytest-mock>=3.14.0 ; extra == "dev"
Requires-Dist: pytest>=8.3.3 ; extra == "dev"
Requires-Dist: ruff>=0.7.1 ; extra == "dev"
Requires-Dist: types-requests>=2.32 ; extra == "dev"
Requires-Dist: types-auth0-python ; extra == "dev"
Provides-Extra: dev
